{
    "date": "2025-02-05 17:34:30.679622",
    "time": [
        "0:00",
        "3:00",
        "6:00",
        "9:00",
        "12:00",
        "15:00",
        "18:00",
        "21:00"
    ],
    "temperature": [
        "-4",
        "-4",
        "-3",
        "-3",
        "-1",
        "-1",
        "-2",
        "-2"
    ],
    "wind direction": [
        "С",
        "С",
        "С",
        "С",
        "СВ",
        "СВ",
        "СВ",
        "СВ"
    ],
    "windspeed": [
        "5",
        "7",
        "8",
        "9",
        "11",
        "10",
        "9",
        "8"
    ],
    "precipitation": [
        "0",
        "0",
        "0",
        "0,4",
        "0,9",
        "0,3",
        "0",
        "0"
    ],
    "pressure": [
        "754",
        "754",
        "753",
        "753",
        "754",
        "755",
        "757",
        "759"
    ],
    "humidity": [
        "91",
        "88",
        "89",
        "93",
        "89",
        "76",
        "85",
        "77"
    ],
    "icons": [
        "#n_c3",
        "#n_c0",
        "#n_c3",
        "#d_c3",
        "#s1",
        "#d_c3",
        "#s2",
        "#d_c3",
        "#rs1",
        "#n_c3",
        "#n_c3"
    ]
}