{
    "date": "2025-07-29 04:29:18.279193",
    "time": [
        "0:00",
        "3:00",
        "6:00",
        "9:00",
        "12:00",
        "15:00",
        "18:00",
        "21:00"
    ],
    "temperature": [
        "18",
        "17",
        "16",
        "25",
        "28",
        "29",
        "28",
        "23"
    ],
    "wind direction": [],
    "windspeed": [],
    "precipitation": [
        "0",
        "0",
        "0",
        "0",
        "0",
        "0",
        "0",
        "0"
    ],
    "pressure": [
        "745",
        "745",
        "745",
        "745",
        "745",
        "745",
        "744",
        "744"
    ],
    "humidity": [
        "84",
        "80",
        "88",
        "61",
        "48",
        "41",
        "44",
        "60"
    ],
    "icons": [
        "#n_c0",
        "#n_c0",
        "#d_c0",
        "#d_c0",
        "#d_c1",
        "#d_c1",
        "#d_c1",
        "#n_c0"
    ]
}